freshdesk_api.py
setup.py
python_freshdesk_client.egg-info/PKG-INFO
python_freshdesk_client.egg-info/SOURCES.txt
python_freshdesk_client.egg-info/dependency_links.txt
python_freshdesk_client.egg-info/pbr.json
python_freshdesk_client.egg-info/requires.txt
python_freshdesk_client.egg-info/top_level.txt