Metadata-Version: 1.1
Name: python-freshdesk-client
Version: 0.2
Summary: Wrapper arround freshdesk REST API
Home-page: UNKNOWN
Author: Jocelyn Delalande
Author-email: jdelalande@oasiswork.fr
License: UNKNOWN
Platform: UNKNOWN
Classifier: License :: OSI Approved :: MIT License
